README.md
setup.py
brcode/__init__.py
brcode/dynamic.py
brcode/static.py
brcode/tests/__init__.py
brcode/tests/brcodeTests/__init__.py
brcode/tests/brcodeTests/testBrcodeId.py
brcode/tests/brcodeTests/testDynamicBrcode.py
brcode/tests/brcodeTests/testStaticBrcode.py
brcode/utils/__init__.py
brcode/utils/accents.py
brcode/utils/brcodeId.py
brcode/utils/brcodeJson.py
brcode/utils/enum.py
starkbank_brcode.egg-info/PKG-INFO
starkbank_brcode.egg-info/SOURCES.txt
starkbank_brcode.egg-info/dependency_links.txt
starkbank_brcode.egg-info/top_level.txt