Metadata-Version: 2.1
Name: starkbank-brcode
Version: 1.0.3
Summary: Python library for conversion between Central Bank's BR Code message standard and JSON
Home-page: https://github.com/starkbank/brcode-python
Author: Stark Bank
Author-email: developers@starkbank.com
License: MIT License
Keywords: stark bank,starkbank,brcode,BR Code,open banking,openbanking,banking,open,stark,Brazil Central Bank
Platform: UNKNOWN
